Workbook

Sheet 近一月指数走势
A1: 自定义更新日期 | B1: 指数简称 | C1: 上证指数 | D1: 中证转债 | E1: 标普500 | F1: 7-10年国开 | G1: 1-3年高信用等级债券财富 | H1: 10年期美国国债收益率 | I1: USDCNY | J1: 沪金 | K1: 螺纹钢 | L1: 原油 | M1: 豆粕 | N1: 锁汇成本
A2: =TODAY()-1 -> 46046 | B2: 指数代码 | C2: 000001.SH | D2: 000832.CSI | E2: SPX.GI | F2: 931472.CSI | G2: CBA01921.CS | H2: 10yrnote.gbm | I2: USDCNY.IB | J2: AU.SHF | K2: RB.SHF | L2: SC.INE | M2: M.DCE | N2: 锁汇成本
B3: =WORKDAY(B4,-1) -> 46015 | C3: {=[1]!i_dq_close($C$2,B3)} -> 3940.947 | D3: {=[1]!s_dq_close($D$2,B3)} -> 490.3799 | E3: {=[1]!s_dq_close($E$2,B3)} -> 6932.05 | F3: {=[1]!s_dq_close($F$2,B3)} -> 186.3625 | G3: {=[1]!s_dq_close($G$2,B3)} -> 227.3546 | H3: {=[1]!s_dq_close($H$2,B3)} -> 4.1355 | I3: {=[1]!s_dq_close($I$2,B3)} -> 7.0161 | J3: {=[1]!s_dq_close($J$2,B3)} -> 1014.68 | K3: {=[1]!s_dq_close($K$2,B3)} -> 3136 | L3: {=[1]!s_dq_close($L$2,B3)} -> 444.7 | M3: {=[1]!s_dq_close($M$2,B3)} -> 2728 | N3: =-[1]!s_dq_close("USDCNY1YS.IB",B3)/10000/[1]!s_dq_close("USDCNH.FX",B3) -> 0.01678178
B4: =WORKDAY(B5,-1) -> 46016 | C4: {=[1]!i_dq_close($C$2,B4)} -> 3959.6211 | D4: {=[1]!s_dq_close($D$2,B4)} -> 493.4639 | E4: {=[1]!s_dq_close($E$2,B4)} -> 6932.05 | F4: {=[1]!s_dq_close($F$2,B4)} -> 186.3011 | G4: {=[1]!s_dq_close($G$2,B4)} -> 227.3918 | H4: {=[1]!s_dq_close($H$2,B4)} -> 4.1355 | I4: {=[1]!s_dq_close($I$2,B4)} -> 7.0066 | J4: {=[1]!s_dq_close($J$2,B4)} -> 1008.76 | K4: {=[1]!s_dq_close($K$2,B4)} -> 3127 | L4: {=[1]!s_dq_close($L$2,B4)} -> 442.7 | M4: {=[1]!s_dq_close($M$2,B4)} -> 2760 | N4: =-[1]!s_dq_close("USDCNY1YS.IB",B4)/10000/[1]!s_dq_close("USDCNH.FX",B4) -> 0.015897729
B5: =WORKDAY(B6,-1) -> 46017 | C5: {=[1]!i_dq_close($C$2,B5)} -> 3963.6789 | D5: {=[1]!s_dq_close($D$2,B5)} -> 493.2493 | E5: {=[1]!s_dq_close($E$2,B5)} -> 6929.94 | F5: {=[1]!s_dq_close($F$2,B5)} -> 186.3134 | G5: {=[1]!s_dq_close($G$2,B5)} -> 227.4183 | H5: {=[1]!s_dq_close($H$2,B5)} -> 4.1277 | I5: {=[1]!s_dq_close($I$2,B5)} -> 7.0085 | J5: {=[1]!s_dq_close($J$2,B5)} -> 1016.3 | K5: {=[1]!s_dq_close($K$2,B5)} -> 3118 | L5: {=[1]!s_dq_close($L$2,B5)} -> 441.8 | M5: {=[1]!s_dq_close($M$2,B5)} -> 2790 | N5: =-[1]!s_dq_close("USDCNY1YS.IB",B5)/10000/[1]!s_dq_close("USDCNH.FX",B5) -> 0.01571914
B6: =WORKDAY(B7,-1) -> 46020 | C6: {=[1]!i_dq_close($C$2,B6)} -> 3965.2796 | D6: {=[1]!s_dq_close($D$2,B6)} -> 491.1448 | E6: {=[1]!s_dq_close($E$2,B6)} -> 6905.74 | F6: {=[1]!s_dq_close($F$2,B6)} -> 185.91 | G6: {=[1]!s_dq_close($G$2,B6)} -> 227.4379 | H6: {=[1]!s_dq_close($H$2,B6)} -> 4.1102 | I6: {=[1]!s_dq_close($I$2,B6)} -> 7.0098 | J6: {=[1]!s_dq_close($J$2,B6)} -> 1007.18 | K6: {=[1]!s_dq_close($K$2,B6)} -> 3130 | L6: {=[1]!s_dq_close($L$2,B6)} -> 434.8 | M6: {=[1]!s_dq_close($M$2,B6)} -> 2774 | N6: =-[1]!s_dq_close("USDCNY1YS.IB",B6)/10000/[1]!s_dq_close("USDCNH.FX",B6) -> 0.016290369
B7: =WORKDAY(B8,-1) -> 46021 | C7: {=[1]!i_dq_close($C$2,B7)} -> 3965.1159 | D7: {=[1]!s_dq_close($D$2,B7)} -> 491.8273 | E7: {=[1]!s_dq_close($E$2,B7)} -> 6896.24 | F7: {=[1]!s_dq_close($F$2,B7)} -> 185.7963 | G7: {=[1]!s_dq_close($G$2,B7)} -> 227.4466 | H7: {=[1]!s_dq_close($H$2,B7)} -> 4.1199 | I7: {=[1]!s_dq_close($I$2,B7)} -> 6.9901 | J7: {=[1]!s_dq_close($J$2,B7)} -> 984.84 | K7: {=[1]!s_dq_close($K$2,B7)} -> 3134 | L7: {=[1]!s_dq_close($L$2,B7)} -> 436.1 | M7: {=[1]!s_dq_close($M$2,B7)} -> 2778 | N7: =-[1]!s_dq_close("USDCNY1YS.IB",B7)/10000/[1]!s_dq_close("USDCNH.FX",B7) -> 0.016260744
B8: =WORKDAY(B9,-1) -> 46022 | C8: {=[1]!i_dq_close($C$2,B8)} -> 3968.8401 | D8: {=[1]!s_dq_close($D$2,B8)} -> 491.9017 | E8: {=[1]!s_dq_close($E$2,B8)} -> 6845.5 | F8: {=[1]!s_dq_close($F$2,B8)} -> 185.8615 | G8: {=[1]!s_dq_close($G$2,B8)} -> 227.4613 | H8: {=[1]!s_dq_close($H$2,B8)} -> 4.1474 | I8: {=[1]!s_dq_close($I$2,B8)} -> 6.989 | J8: {=[1]!s_dq_close($J$2,B8)} -> 977.56 | K8: {=[1]!s_dq_close($K$2,B8)} -> 3122 | L8: {=[1]!s_dq_close($L$2,B8)} -> 432.2 | M8: {=[1]!s_dq_close($M$2,B8)} -> 2749 | N8: =-[1]!s_dq_close("USDCNY1YS.IB",B8)/10000/[1]!s_dq_close("USDCNH.FX",B8) -> 0.016142212
B9: =WORKDAY(B10,-1) -> 46023 | C9: {=[1]!i_dq_close($C$2,B9)} -> 3968.8401 | D9: {=[1]!s_dq_close($D$2,B9)} -> 491.9017 | E9: {=[1]!s_dq_close($E$2,B9)} -> 6845.5 | F9: {=[1]!s_dq_close($F$2,B9)} -> 185.8615 | G9: {=[1]!s_dq_close($G$2,B9)} -> 227.4613 | H9: {=[1]!s_dq_close($H$2,B9)} -> 4.1769 | I9: {=[1]!s_dq_close($I$2,B9)} -> 6.989 | J9: {=[1]!s_dq_close($J$2,B9)} -> 977.56 | K9: {=[1]!s_dq_close($K$2,B9)} -> 3122 | L9: {=[1]!s_dq_close($L$2,B9)} -> 432.2 | M9: {=[1]!s_dq_close($M$2,B9)} -> 2749 | N9: =-[1]!s_dq_close("USDCNY1YS.IB",B9)/10000/[1]!s_dq_close("USDCNH.FX",B9) -> 0.016131805
B10: =WORKDAY(B11,-1) -> 46024 | C10: {=[1]!i_dq_close($C$2,B10)} -> 3968.8401 | D10: {=[1]!s_dq_close($D$2,B10)} -> 491.9017 | E10: {=[1]!s_dq_close($E$2,B10)} -> 6858.47 | F10: {=[1]!s_dq_close($F$2,B10)} -> 185.8615 | G10: {=[1]!s_dq_close($G$2,B10)} -> 227.4613 | H10: {=[1]!s_dq_close($H$2,B10)} -> 4.1907 | I10: {=[1]!s_dq_close($I$2,B10)} -> 6.989 | J10: {=[1]!s_dq_close($J$2,B10)} -> 977.56 | K10: {=[1]!s_dq_close($K$2,B10)} -> 3122 | L10: {=[1]!s_dq_close($L$2,B10)} -> 432.2 | M10: {=[1]!s_dq_close($M$2,B10)} -> 2749 | N10: =-[1]!s_dq_close("USDCNY1YS.IB",B10)/10000/[1]!s_dq_close("USDCNH.FX",B10) -> 0.016155182
B11: =WORKDAY(B12,-1) -> 46027 | C11: {=[1]!i_dq_close($C$2,B11)} -> 4023.4167 | D11: {=[1]!s_dq_close($D$2,B11)} -> 499.0064 | E11: {=[1]!s_dq_close($E$2,B11)} -> 6902.05 | F11: {=[1]!s_dq_close($F$2,B11)} -> 185.9114 | G11: {=[1]!s_dq_close($G$2,B11)} -> 227.5618 | H11: {=[1]!s_dq_close($H$2,B11)} -> 4.1651 | I11: {=[1]!s_dq_close($I$2,B11)} -> 6.9806 | J11: {=[1]!s_dq_close($J$2,B11)} -> 995 | K11: {=[1]!s_dq_close($K$2,B11)} -> 3104 | L11: {=[1]!s_dq_close($L$2,B11)} -> 421.7 | M11: {=[1]!s_dq_close($M$2,B11)} -> 2754 | N11: =-[1]!s_dq_close("USDCNY1YS.IB",B11)/10000/[1]!s_dq_close("USDCNH.FX",B11) -> 0.016683613
B12: =WORKDAY(B13,-1) -> 46028 | C12: {=[1]!i_dq_close($C$2,B12)} -> 4083.6672 | D12: {=[1]!s_dq_close($D$2,B12)} -> 505.7676 | E12: {=[1]!s_dq_close($E$2,B12)} -> 6944.82 | F12: {=[1]!s_dq_close($F$2,B12)} -> 185.5683 | G12: {=[1]!s_dq_close($G$2,B12)} -> 227.5593 | H12: {=[1]!s_dq_close($H$2,B12)} -> 4.1691 | I12: {=[1]!s_dq_close($I$2,B12)} -> 6.9813 | J12: {=[1]!s_dq_close($J$2,B12)} -> 1004.98 | K12: {=[1]!s_dq_close($K$2,B12)} -> 3111 | L12: {=[1]!s_dq_close($L$2,B12)} -> 428.2 | M12: {=[1]!s_dq_close($M$2,B12)} -> 2776 | N12: =-[1]!s_dq_close("USDCNY1YS.IB",B12)/10000/[1]!s_dq_close("USDCNH.FX",B12) -> 0.016860532
B13: =WORKDAY(B14,-1) -> 46029 | C13: {=[1]!i_dq_close($C$2,B13)} -> 4085.7723 | D13: {=[1]!s_dq_close($D$2,B13)} -> 507.2762 | E13: {=[1]!s_dq_close($E$2,B13)} -> 6920.93 | F13: {=[1]!s_dq_close($F$2,B13)} -> 185.3597 | G13: {=[1]!s_dq_close($G$2,B13)} -> 227.5455 | H13: {=[1]!s_dq_close($H$2,B13)} -> 4.1475 | I13: {=[1]!s_dq_close($I$2,B13)} -> 6.9912 | J13: {=[1]!s_dq_close($J$2,B13)} -> 998.9 | K13: {=[1]!s_dq_close($K$2,B13)} -> 3187 | L13: {=[1]!s_dq_close($L$2,B13)} -> 416.3 | M13: {=[1]!s_dq_close($M$2,B13)} -> 2811 | N13: =-[1]!s_dq_close("USDCNY1YS.IB",B13)/10000/[1]!s_dq_close("USDCNH.FX",B13) -> 0.017330378
B14: =WORKDAY(B15,-1) -> 46030 | C14: {=[1]!i_dq_close($C$2,B14)} -> 4082.9788 | D14: {=[1]!s_dq_close($D$2,B14)} -> 509.2569 | E14: {=[1]!s_dq_close($E$2,B14)} -> 6921.46 | F14: {=[1]!s_dq_close($F$2,B14)} -> 185.6283 | G14: {=[1]!s_dq_close($G$2,B14)} -> 227.554 | H14: {=[1]!s_dq_close($H$2,B14)} -> 4.1633 | I14: {=[1]!s_dq_close($I$2,B14)} -> 6.9807 | J14: {=[1]!s_dq_close($J$2,B14)} -> 997.94 | K14: {=[1]!s_dq_close($K$2,B14)} -> 3168 | L14: {=[1]!s_dq_close($L$2,B14)} -> 416.2 | M14: {=[1]!s_dq_close($M$2,B14)} -> 2782 | N14: =-[1]!s_dq_close("USDCNY1YS.IB",B14)/10000/[1]!s_dq_close("USDCNH.FX",B14) -> 0.017143348
... B24: =WORKDAY(B25,-1) -> 46044 | C24: {=[1]!i_dq_close($C$2,B24)} -> 4122.576 | D24: {=[1]!s_dq_close($D$2,B24)} -> 527.7333 | E24: {=[1]!s_dq_close($E$2,B24)} -> 6913.35 | F24: {=[1]!s_dq_close($F$2,B24)} -> 186.3597 | G24: {=[1]!s_dq_close($G$2,B24)} -> 227.8801 | H24: {=[1]!s_dq_close($H$2,B24)} -> 4.2409 | I24: {=[1]!s_dq_close($I$2,B24)} -> 6.9628 | J24: {=[1]!s_dq_close($J$2,B24)} -> 1087.58 | K24: {=[1]!s_dq_close($K$2,B24)} -> 3124 | L24: {=[1]!s_dq_close($L$2,B24)} -> 446.4 | M24: {=[1]!s_dq_close($M$2,B24)} -> 2768 | N24: =-[1]!s_dq_close("USDCNY1YS.IB",B24)/10000/[1]!s_dq_close("USDCNH.FX",B24) -> 0.017475589
B25: =WORKDAY(A2,-1) -> 46045 | C25: {=[1]!i_dq_close($C$2,B25)} -> 4136.1642 | D25: {=[1]!s_dq_close($D$2,B25)} -> 534.4828 | E25: {=[1]!s_dq_close($E$2,B25)} -> 6915.61 | F25: {=[1]!s_dq_close($F$2,B25)} -> 186.5544 | G25: {=[1]!s_dq_close($G$2,B25)} -> 227.9117 | H25: {=[1]!s_dq_close($H$2,B25)} -> 4.2212 | I25: {=[1]!s_dq_close($I$2,B25)} -> 6.9642 | J25: {=[1]!s_dq_close($J$2,B25)} -> 1115.64 | K25: {=[1]!s_dq_close($K$2,B25)} -> 3142 | L25: {=[1]!s_dq_close($L$2,B25)} -> 441.9 | M25: {=[1]!s_dq_close($M$2,B25)} -> 2751 | N25: =-[1]!s_dq_close("USDCNY1YS.IB",B25)/10000/[1]!s_dq_close("USDCNH.FX",B25) -> 0.0177875

Sheet 指标值
A1: 大类资产 | B1: 子类资产 | C1: 观察指标（近三年） | D1: 当前值 | E1: 最大值 | F1: 最小值 | G1: 历史中位数 | H1: 当前分位点 | I1: 对应列 | J1: 对应位置
A2: 权益 | B2: 上证指数 | C2: PE | D2: =股票指标!B3 -> 17.0912 | E2: =MAX(INDIRECT(J2)) -> 17.1359 | F2: =MIN(INDIRECT(J2)) -> 11.7482 | G2: =MEDIAN(INDIRECT(J2)) -> 13.5578 | H2: =_xlfn.PERCENTRANK.INC(INDIRECT(J2), D2) -> 0.993 | I2: 股票指标!B | J2: =I2&":"&RIGHT(I2,1) -> 股票指标!B:B
A3: 权益 | B3: 上证指数 | C3: PB | D3: =股票指标!C3 -> 1.5524 | E3: =MAX(INDIRECT(J3)) -> 1.5535001 | F3: =MIN(INDIRECT(J3)) -> 1.1191 | G3: =MEDIAN(INDIRECT(J3)) -> 1.3142 | H3: =_xlfn.PERCENTRANK.INC(INDIRECT(J3), D3) -> 0.993 | I3: 股票指标!C | J3: =I3&":"&RIGHT(I3,1) -> 股票指标!C:C
A4: 权益 | B4: 上证指数 | C4: 股债性价比 | D4: =股票指标!D3 -> 0.040211643 | E4: =MAX(INDIRECT(J4)) -> 0.062816769 | F4: =MIN(INDIRECT(J4)) -> 0.039575015 | G4: =MEDIAN(INDIRECT(J4)) -> 0.05088502 | H4: =1-_xlfn.PERCENTRANK.INC(INDIRECT(J4), D4) -> 0.994 | I4: 股票指标!D | J4: =I4&":"&RIGHT(I4,1) -> 股票指标!D:D
A5: 权益 | B5: 中证转债 | C5: 转股溢价率 | D5: =股票指标!E3 -> 0.30935085 | E5: =MAX(INDIRECT(J5)) -> 0.64611 | F5: =MIN(INDIRECT(J5)) -> 0.22559961 | G5: =MEDIAN(INDIRECT(J5)) -> 0.37811431 | H5: =_xlfn.PERCENTRANK.INC(INDIRECT(J5), D5) -> 0.111 | I5: 股票指标!E | J5: =I5&":"&RIGHT(I5,1) -> 股票指标!E:E
A6: 权益 | B6: 中证转债 | C6: 纯债溢价率 | D6: =股票指标!F3 -> 0.1776822 | E6: =MAX(INDIRECT(J6)) -> 0.37259104 | F6: =MIN(INDIRECT(J6)) -> -0.0018727755 | G6: =MEDIAN(INDIRECT(J6)) -> 0.25043993 | H6: =_xlfn.PERCENTRANK.INC(INDIRECT(J6), D6) -> 0.375 | I6: 股票指标!F | J6: =I6&":"&RIGHT(I6,1) -> 股票指标!F:F
A7: 权益 | B7: 中证转债 | C7: 隐含波动率 | D7: =股票指标!G3 -> 0.35448332 | E7: =MAX(INDIRECT(J7)) -> 0.51443062 | F7: =MIN(INDIRECT(J7)) -> 6.6129442e-08 | G7: =MEDIAN(INDIRECT(J7)) -> 0.42502788 | H7: =_xlfn.PERCENTRANK.INC(INDIRECT(J7), D7) -> 0.296 | I7: 股票指标!G | J7: =I7&":"&RIGHT(I7,1) -> 股票指标!G:G
A8: 权益 | B8: 标普500 | C8: PE | D8: =股票指标!H3 -> 29.515699 | E8: =MAX(INDIRECT(J8)) -> 29.7992 | F8: =MIN(INDIRECT(J8)) -> 21.6397 | G8: =MEDIAN(INDIRECT(J8)) -> 26.2572 | H8: =_xlfn.PERCENTRANK.INC(INDIRECT(J8), D8) -> 0.967 | I8: 股票指标!H | J8: =I8&":"&RIGHT(I8,1) -> 股票指标!H:H
A9: 权益 | B9: 标普500 | C9: PB | D9: =股票指标!I3 -> 5.5702 | E9: =MAX(INDIRECT(J9)) -> 5.6240001 | F9: =MIN(INDIRECT(J9)) -> 3.6908 | G9: =MEDIAN(INDIRECT(J9)) -> 4.7662001 | H9: =_xlfn.PERCENTRANK.INC(INDIRECT(J9), D9) -> 0.98 | I9: 股票指标!I | J9: =I9&":"&RIGHT(I9,1) -> 股票指标!I:I
A10: 权益 | B10: 标普500 | C10: 股债性价比 | D10: =股票指标!J3 -> -0.0085197254 | E10: =MAX(INDIRECT(J10)) -> 0.010742261 | F10: =MIN(INDIRECT(J10)) -> -0.01225208 | G10: =MEDIAN(INDIRECT(J10)) -> -0.0050039446 | H10: =_xlfn.PERCENTRANK.INC(INDIRECT(J10), D10) -> 0.111 | I10: 股票指标!J | J10: =I10&":"&RIGHT(I10,1) -> 股票指标!J:J
A11: 债券 | B11: 7-10年国开 | C11: 收益率 | D11: =债券指标!B3 -> 1.9735 | E11: =MAX(INDIRECT(J11)) -> 3.0916 | F11: =MIN(INDIRECT(J11)) -> 1.6067 | G11: =MEDIAN(INDIRECT(J11)) -> 2.253 | H11: =_xlfn.PERCENTRANK.INC(INDIRECT(J11), D11) -> 0.289 | I11: 债券指标!B | J11: =I11&":"&RIGHT(I11,1) -> 债券指标!B:B
A12: 债券 | B12: 7-10年国开 | C12: 信用利差 | D12: =债券指标!C3 -> 14.37 | E12: =MAX(INDIRECT(J12)) -> 18.9 | F12: =MIN(INDIRECT(J12)) -> -1.74 | G12: =MEDIAN(INDIRECT(J12)) -> 8.93 | H12: =_xlfn.PERCENTRANK.INC(INDIRECT(J12), D12) -> 0.789 | I12: 债券指标!C | J12: =I12&":"&RIGHT(I12,1) -> 债券指标!C:C
A13: 债券 | B13: 7-10年国开 | C13: 期限利差 | D13: =债券指标!D3 -> 39.76 | E13: =MAX(INDIRECT(J13)) -> 75.57 | F13: =MIN(INDIRECT(J13)) -> 6.08 | G13: =MEDIAN(INDIRECT(J13)) -> 47.88 | H13: =_xlfn.PERCENTRANK.INC(INDIRECT(J13), D13) -> 0.375 | I13: 债券指标!D | J13: =I13&":"&RIGHT(I13,1) -> 债券指标!D:D
A14: 债券 | B14: 1-3年高信用等级债券财富 | C14: 收益率 | D14: =债券指标!E3 -> 1.7741 | E14: =MAX(INDIRECT(J14)) -> 3.0806 | F14: =MIN(INDIRECT(J14)) -> 1.6316 | G14: =MEDIAN(INDIRECT(J14)) -> 2.0962 | H14: =_xlfn.PERCENTRANK.INC(INDIRECT(J14), D14) -> 0.059 | I14: 债券指标!E | J14: =I14&":"&RIGHT(I14,1) -> 债券指标!E:E
A15: 债券 | B15: 1-3年高信用等级债券财富 | C15: 信用利差 | D15: =债券指标!F3 -> 37.82 | E15: =MAX(INDIRECT(J15)) -> 80.08 | F15: =MIN(INDIRECT(J15)) -> 31.57 | G15: =MEDIAN(INDIRECT(J15)) -> 44.32 | H15: =_xlfn.PERCENTRANK.INC(INDIRECT(J15), D15) -> 0.203 | I15: 债券指标!F | J15: =I15&":"&RIGHT(I15,1) -> 债券指标!F:F
A16: 债券 | B16: 1-3年高信用等级债券财富 | C16: 期限利差 | D16: =债券指标!G3 -> 10.2 | E16: =MAX(INDIRECT(J16)) -> 24.2 | F16: =MIN(INDIRECT(J16)) -> -0.6 | G16: =MEDIAN(INDIRECT(J16)) -> 10.75 | H16: =_xlfn.PERCENTRANK.INC(INDIRECT(J16), D16) -> 0.434 | I16: 债券指标!G | J16: =I16&":"&RIGHT(I16,1) -> 债券指标!G:G
A17: 债券 | B17: 10年期美国国债收益率 | C17: 收益率 | D17: =债券指标!H3 -> 4.24 | E17: =MAX(INDIRECT(J17)) -> 4.93 | F17: =MIN(INDIRECT(J17)) -> 3.38 | G17: =MEDIAN(INDIRECT(J17)) -> 4.22 | H17: =_xlfn.PERCENTRANK.INC(INDIRECT(J17), D17) -> 0.526 | I17: 债券指标!H | J17: =I17&":"&RIGHT(I17,1) -> 债券指标!H:H
A18: 债券 | B18: 10年期美国国债收益率 | C18: 期限利差(10减1） | D18: =债券指标!I3 -> 71 | E18: =MAX(INDIRECT(J18)) -> 72 | F18: =MIN(INDIRECT(J18)) -> -159 | G18: =MEDIAN(INDIRECT(J18)) -> -54 | H18: =_xlfn.PERCENTRANK.INC(INDIRECT(J18), D18) -> 0.993 | I18: 债券指标!I | J18: =I18&":"&RIGHT(I18,1) -> 债券指标!I:I
A19: 债券 | B19: 10年期美国国债收益率 | C19: FF | D19: =债券指标!J3 -> 16.09 | E19: =MAX(INDIRECT(J19)) -> 45.31 | F19: =MIN(INDIRECT(J19)) -> 11.93 | G19: =MEDIAN(INDIRECT(J19)) -> 15.97 | H19: =_xlfn.PERCENTRANK.INC(INDIRECT(J19), D19) -> 0.513 | I19: 债券指标!J | J19: =I19&":"&RIGHT(I19,1) -> 债券指标!J:J | O19: 现在只剩权益 中证转债 转股溢价率
A20: 汇率 | B20: 锁汇成本 | C20: 锁汇成本 | D20: =汇率指标!E3 -> 0.0177875 | E20: =MAX(INDIRECT(J20)) -> 0.040440572 | F20: =MIN(INDIRECT(J20)) -> 0.01571914 | G20: =MEDIAN(INDIRECT(J20)) -> 0.030890045 | H20: =_xlfn.PERCENTRANK.INC(INDIRECT(J20), D20) -> 0.046 | I20: 汇率指标!E | J20: =I20&":"&RIGHT(I20,1) -> 汇率指标!E:E | O20: 权益 中证转债 纯债溢价率
A21: 汇率 | B21: 锁汇成本 | C21: 掉期点1Y | D21: =汇率指标!F3 -> -1236 | E21: =MAX(INDIRECT(J21)) -> -1101 | F21: =MIN(INDIRECT(J21)) -> -2952 | G21: =MEDIAN(INDIRECT(J21)) -> -2242 | H21: =_xlfn.PERCENTRANK.INC(INDIRECT(J21), D21) -> 0.967 | I21: 汇率指标!F | J21: =I21&":"&RIGHT(I21,1) -> 汇率指标!F:F | O21: 权益 中证转债 隐含波动率这几个指标没有了，w.wsd("000832.CSI", "strbpremiumratio,convpremiumratio,impliedvol", "2025-12-25", "2026-01-25", "rfIndex=1;")
A22: 汇率 | B22: 锁汇成本 | C22: 美元兑离岸人民币CNH | D22: =汇率指标!G3 -> 6.9487 | E22: =MAX(INDIRECT(J22)) -> 7.365 | F22: =MIN(INDIRECT(J22)) -> 6.8707 | G22: =MEDIAN(INDIRECT(J22)) -> 7.1896 | H22: =_xlfn.PERCENTRANK.INC(INDIRECT(J22), D22) -> 0.065 | I22: 汇率指标!G | J22: =I22&":"&RIGHT(I22,1) -> 汇率指标!G:G | O22: 我尝试使用这个代码来获取，但好像只有转股溢价率可以获取到数据，其他的指标可能需要通过获取中证转债这个指数的成分转债指数，然后获取成本券的这些指标值，然后通过平均值来计算得出
A23: 汇率 | B23: USDCNY | C23: 中间价 | D23: =汇率指标!B3 -> 6.9642 | E23: =MAX(INDIRECT(J23)) -> 7.3415 | F23: =MIN(INDIRECT(J23)) -> 6.8495 | G23: =MEDIAN(INDIRECT(J23)) -> 7.1837 | H23: =_xlfn.PERCENTRANK.INC(INDIRECT(J23), D23) -> 0.072 | I23: 汇率指标!B | J23: =I23&":"&RIGHT(I23,1) -> 汇率指标!B:B
A24: 汇率 | B24: USDCNY | C24: 中美利差 | D24: =汇率指标!C3 -> -241.02 | E24: =MAX(INDIRECT(J24)) -> -51.24 | F24: =MIN(INDIRECT(J24)) -> -313.62 | G24: =MEDIAN(INDIRECT(J24)) -> -211.74 | H24: =_xlfn.PERCENTRANK.INC(INDIRECT(J24), D24) -> 0.23 | I24: 汇率指标!C | J24: =I24&":"&RIGHT(I24,1) -> 汇率指标!C:C
A25: 汇率 | B25: USDCNY | C25: 美元指数 | D25: =汇率指标!D3 -> 97.5053 | E25: =MAX(INDIRECT(J25)) -> 109.6567 | F25: =MIN(INDIRECT(J25)) -> 96.988 | G25: =MEDIAN(INDIRECT(J25)) -> 103.1952 | H25: =_xlfn.PERCENTRANK.INC(INDIRECT(J25), D25) -> 0.013 | I25: 汇率指标!D | J25: =I25&":"&RIGHT(I25,1) -> 汇率指标!D:D
A26: 商品 | B26: 沪金 | C26: 内外盘价差 | D26: =商品指标!B3 -> -0.096332567 | E26: =MAX(INDIRECT(J26)) -> 25.996716 | F26: =MIN(INDIRECT(J26)) -> -22.634178 | G26: =MEDIAN(INDIRECT(J26)) -> 1.8523661 | H26: =_xlfn.PERCENTRANK.INC(INDIRECT(J26), D26) -> 0.394 | I26: 商品指标!B | J26: =I26&":"&RIGHT(I26,1) -> 商品指标!B:B
A27: 商品 | B27: 沪金 | C27: 美国实际利率 | D27: =商品指标!C3 -> 1.92 | E27: =MAX(INDIRECT(J27)) -> 2.47 | F27: =MIN(INDIRECT(J27)) -> 1.14 | G27: =MEDIAN(INDIRECT(J27)) -> 1.92 | H27: =_xlfn.PERCENTRANK.INC(INDIRECT(J27), D27) -> 0.486 | I27: 商品指标!C | J27: =I27&":"&RIGHT(I27,1) -> 商品指标!C:C
A28: 商品 | B28: 沪金 | C28: USDCNY中间价 | D28: =商品指标!D3 -> 6.9642 | E28: =MAX(INDIRECT(J28)) -> 7.3415 | F28: =MIN(INDIRECT(J28)) -> 6.8495 | G28: =MEDIAN(INDIRECT(J28)) -> 7.1837 | H28: =_xlfn.PERCENTRANK.INC(INDIRECT(J28), D28) -> 0.072 | I28: 商品指标!D | J28: =I28&":"&RIGHT(I28,1) -> 商品指标!D:D
A29: 商品 | B29: 螺纹钢 | C29: 螺卷差（热卷减螺纹） | D29: =商品指标!E3 -> 163 | E29: =MAX(INDIRECT(J29)) -> 266 | F29: =MIN(INDIRECT(J29)) -> 45 | G29: =MEDIAN(INDIRECT(J29)) -> 131 | H29: =_xlfn.PERCENTRANK.INC(INDIRECT(J29), D29) -> 0.677 | I29: 商品指标!E | J29: =I29&":"&RIGHT(I29,1) -> 商品指标!E:E
A30: 商品 | B30: 螺纹钢 | C30: 铁矿价格 | D30: =商品指标!F3 -> 795 | E30: =MAX(INDIRECT(J30)) -> 1000 | F30: =MIN(INDIRECT(J30)) -> 680 | G30: =MEDIAN(INDIRECT(J30)) -> 797 | H30: =_xlfn.PERCENTRANK.INC(INDIRECT(J30), D30) -> 0.48 | I30: 商品指标!F | J30: =I30&":"&RIGHT(I30,1) -> 商品指标!F:F
A31: 商品 | B31: 螺纹钢 | C31: USDCNY中间价 | D31: =商品指标!G3 -> 6.9642 | E31: =MAX(INDIRECT(J31)) -> 7.3415 | F31: =MIN(INDIRECT(J31)) -> 6.8495 | G31: =MEDIAN(INDIRECT(J31)) -> 7.1837 | H31: =_xlfn.PERCENTRANK.INC(INDIRECT(J31), D31) -> 0.072 | I31: 商品指标!G | J31: =I31&":"&RIGHT(I31,1) -> 商品指标!G:G
A32: 商品 | B32: 原油 | C32: WIT与布油价差 | D32: =商品指标!H3 -> -4.16 | E32: =MAX(INDIRECT(J32)) -> -1.27 | F32: =MIN(INDIRECT(J32)) -> -6.4 | G32: =MEDIAN(INDIRECT(J32)) -> -3.74 | H32: =_xlfn.PERCENTRANK.INC(INDIRECT(J32), D32) -> 0.335 | I32: 商品指标!H | J32: =I32&":"&RIGHT(I32,1) -> 商品指标!H:H
A33: 商品 | B33: 原油 | C33: 美元指数 | D33: =商品指标!I3 -> 97.5053 | E33: =MAX(INDIRECT(J33)) -> 109.6567 | F33: =MIN(INDIRECT(J33)) -> 96.988 | G33: =MEDIAN(INDIRECT(J33)) -> 103.1952 | H33: =_xlfn.PERCENTRANK.INC(INDIRECT(J33), D33) -> 0.013 | I33: 商品指标!I | J33: =I33&":"&RIGHT(I33,1) -> 商品指标!I:I
A34: 商品 | B34: 原油 | C34: USDCNY中间价 | D34: =商品指标!J3 -> 6.9642 | E34: =MAX(INDIRECT(J34)) -> 7.3415 | F34: =MIN(INDIRECT(J34)) -> 6.8495 | G34: =MEDIAN(INDIRECT(J34)) -> 7.1837 | H34: =_xlfn.PERCENTRANK.INC(INDIRECT(J34), D34) -> 0.072 | I34: 商品指标!J | J34: =I34&":"&RIGHT(I34,1) -> 商品指标!J:J
A35: 商品 | B35: 豆粕 | C35: 期货现货价差 | D35: =商品指标!K3 -> -443.29 | E35: =MAX(INDIRECT(J35)) -> 86.57 | F35: =MIN(INDIRECT(J35)) -> -893.86 | G35: =MEDIAN(INDIRECT(J35)) -> -230.29 | H35: =_xlfn.PERCENTRANK.INC(INDIRECT(J35), D35) -> 0.256 | I35: 商品指标!K | J35: =I35&":"&RIGHT(I35,1) -> 商品指标!K:K
A36: 商品 | B36: 豆粕 | C36: 期货主连持仓量 | D36: =商品指标!L3 -> 2161911 | E36: =MAX(INDIRECT(J36)) -> 2666258 | F36: =MIN(INDIRECT(J36)) -> 628233 | G36: =MEDIAN(INDIRECT(J36)) -> 1649188 | H36: =_xlfn.PERCENTRANK.INC(INDIRECT(J36), D36) -> 0.809 | I36: 商品指标!L | J36: =I36&":"&RIGHT(I36,1) -> 商品指标!L:L
A37: 商品 | B37: 豆粕 | C37: USDCNY中间价 | D37: =商品指标!M3 -> 6.9642 | E37: =MAX(INDIRECT(J37)) -> 7.3415 | F37: =MIN(INDIRECT(J37)) -> 6.8495 | G37: =MEDIAN(INDIRECT(J37)) -> 7.1837 | H37: =_xlfn.PERCENTRANK.INC(INDIRECT(J37), D37) -> 0.072 | I37: 商品指标!M | J37: =I37&":"&RIGHT(I37,1) -> 商品指标!M:M

Sheet 所有指标
A1: =[1]!edb() -> Wind
A2: 指标名称 | B2: 中债国债到期收益率:10年:周:最后一条:结束日7 | C2: 中债国开债到期收益率:10年:周:最后一条:结束日7 | D2: 中债中短期票据到期收益率(AAA):2年:周:最后一条:结束日7 | E2: 美国:国债收益率:10年:周:最后一条:结束日7 | F2: 中债国开债到期收益率:1年:周:最后一条:结束日7 | G2: 中债中短期票据到期收益率(AAA):1年:周:最后一条:结束日7 | H2: 美国:国债收益率:1年:周:最后一条:结束日7 | I2: 中债国债到期收益率:2年:周:最后一条:结束日7 | J2: 美国:国债实际收益率:10年:周:最后一条:结束日7 | K2: 中国:日均产量:粗钢:重点企业:周:最后一条:结束日7
A3: 频率 | B3: 周 | C3: 周 | D3: 周 | E3: 周 | F3: 周 | G3: 周 | H3: 周 | I3: 周 | J3: 周 | K3: 周
A4: 单位 | B4: % | C4: % | D4: % | E4: % | F4: % | G4: % | H4: % | I4: % | J4: % | K4: 万吨/天
A5: 指标ID | B5: s1 | C5: s2 | D5: s3 | E5: s4 | F5: s7 | G5: s5 | H5: s6 | I5: s8 | J5: s9 | K5: s10 | M5: 上证PE | N5: sp500PE | O5: 上证PB | P5: sp500PB | Q5: 转股溢价率 | R5: 平价溢价率 | S5: 纯债溢价率 | T5: VIX.GI | U5: USDCNY | V5: 美元指数 | W5: 沪金 | X5: COMEX黄金 | Y5: WTI原油 | Z5: 布油 | AA5: 豆粕持仓量 | AB5: 豆粕期货 | AC5: 豆粕现货 | AD5: 螺纹 | AE5: 热卷 | AF5: 铁矿 | AG5: 美元兑人民币1年掉期 | AH5: 美元兑离岸人民币
A6: 来源 | B6: 中债估值中心 | C6: 中债估值中心 | D6: 中债估值中心 | E6: 美国财政部 | F6: 中债估值中心 | G6: 中债估值中心 | H6: 美国财政部 | I6: 中债估值中心 | J6: 美国财政部 | K6: 钢之家 | M6: 000001.SH | N6: SPX.GI | O6: 000001.SH | P6: SPX.GI | Q6: 000832.CSI | R6: 000832.CSI | S6: 000832.CSI | T6: VIX.GI | U6: USDCNY.IB | V6: USDX.FX | W6: AU.SHF | X6: GC.CMX | Y6: CL.NYM | Z6: B.IPE | AA6: M.DCE | AB6: M.DCE | AC6: W00003SPT.NM | AD6: RB.SHF | AE6: HC.SHF | AF6: I.DCE | AG6: USDCNY1YS.IB | AH6: USDCNH.FX
A7: 46047 | B7: 1.8298 | C7: 1.9735 | D7: 1.7741 | E7: 4.24 | F7: 1.5759 | G7: 1.6721 | H7: 3.53 | I7: 1.3959 | J7: 1.92 | K7: 197.9 | M7: {=[1]!s_val_pe_ttm(M$6,$A7)} -> 17.0912 | N7: {=[1]!s_val_pe_ttm(N$6,$A7)} -> 29.515699 | O7: {=[1]!s_val_pb_lf(O$6,$A7)} -> 1.5524 | P7: {=[1]!s_val_pb_lf(P$6,$A7)} -> 5.5702 | Q7: =[1]!cb_anal_convpremiumratio($Q$6,A7-2) -> 44.831425 | S7: =[1]!cb_anal_straightbondpremiumratio($S$6,A7-3) -> 0 | T7: {=[1]!s_dq_close(T$6,$A7,1)} -> 16.09 | U7: {=[1]!s_dq_close(U$6,$A7,1)} -> 6.9642 | V7: {=[1]!s_dq_close(V$6,$A7,1)} -> 97.5053 | W7: {=[1]!s_dq_close(W$6,$A7,1)} -> 1115.64 | X7: {=[1]!s_dq_close(X$6,$A7,1)} -> 4983.1 | Y7: {=[1]!s_dq_close(Y$6,$A7,1)} -> 61.28 | Z7: {=[1]!s_dq_close(Z$6,$A7,1)} -> 65.44 | AA7: {=[1]!s_dq_oi(AA$6,$A7)} -> 2161911 | AB7: {=[1]!s_dq_close(AB$6,$A7,1)} -> 2751 | AC7: {=[1]!s_dq_close(AC$6,$A7,1)} -> 3194.29 | AD7: {=[1]!s_dq_close(AD$6,$A7,1)} -> 3142 | AE7: {=[1]!s_dq_close(AE$6,$A7,1)} -> 3305 | AF7: {=[1]!s_dq_close(AF$6,$A7,1)} -> 795 | AG7: =[1]!s_dq_close($AG$6,$A7) -> -1236 | AH7: =[1]!s_dq_close($AH$6,A7) -> 6.9487
A8: 46040 | B8: 1.8424 | C8: 2.0152 | D8: 1.7915 | E8: 4.24 | F8: 1.5942 | G8: 1.6986 | H8: 3.55 | I8: 1.4043 | J8: 1.91 | K8: 0 | M8: {=[1]!s_val_pe_ttm(M$6,$A8)} -> 17.0165 | N8: {=[1]!s_val_pe_ttm(N$6,$A8)} -> 29.608299 | O8: {=[1]!s_val_pb_lf(O$6,$A8)} -> 1.5445 | P8: {=[1]!s_val_pb_lf(P$6,$A8)} -> 5.5998998 | Q8: =[1]!cb_anal_convpremiumratio($Q$6,A8-2) -> 46.39792 | S8: =[1]!cb_anal_straightbondpremiumratio($S$6,A8-3) -> 0 | T8: {=[1]!s_dq_close(T$6,$A8,1)} -> 15.86 | U8: {=[1]!s_dq_close(U$6,$A8,1)} -> 6.969 | V8: {=[1]!s_dq_close(V$6,$A8,1)} -> 99.3691 | W8: {=[1]!s_dq_close(W$6,$A8,1)} -> 1032.32 | X8: {=[1]!s_dq_close(X$6,$A8,1)} -> 4601.1 | Y8: {=[1]!s_dq_close(Y$6,$A8,1)} -> 59.22 | Z8: {=[1]!s_dq_close(Z$6,$A8,1)} -> 64.2 | AA8: {=[1]!s_dq_oi(AA$6,$A8)} -> 2238668 | AB8: {=[1]!s_dq_close(AB$6,$A8,1)} -> 2727 | AC8: {=[1]!s_dq_close(AC$6,$A8,1)} -> 3196.29 | AD8: {=[1]!s_dq_close(AD$6,$A8,1)} -> 3163 | AE8: {=[1]!s_dq_close(AE$6,$A8,1)} -> 3315 | AF8: {=[1]!s_dq_close(AF$6,$A8,1)} -> 812 | AG8: =[1]!s_dq_close($AG$6,$A8) -> -1207 | AH8: =[1]!s_dq_close($AH$6,A8) -> 6.9674
A9: 46033 | B9: 1.8782 | C9: 2.0287 | D9: 1.8057 | E9: 4.18 | F9: 1.5779 | G9: 1.6938 | H9: 3.52 | I9: 1.4362 | J9: 1.9 | K9: 199.7 | M9: {=[1]!s_val_pe_ttm(M$6,$A9)} -> 17.1359 | N9: {=[1]!s_val_pe_ttm(N$6,$A9)} -> 29.7474 | O9: {=[1]!s_val_pb_lf(O$6,$A9)} -> 1.5535001 | P9: {=[1]!s_val_pb_lf(P$6,$A9)} -> 5.6240001 | Q9: =[1]!cb_anal_convpremiumratio($Q$6,A9-2) -> 46.748834 | S9: =[1]!cb_anal_straightbondpremiumratio($S$6,A9-3) -> 0 | T9: {=[1]!s_dq_close(T$6,$A9,1)} -> 14.49 | U9: {=[1]!s_dq_close(U$6,$A9,1)} -> 6.9821 | V9: {=[1]!s_dq_close(V$6,$A9,1)} -> 99.1368 | W9: {=[1]!s_dq_close(W$6,$A9,1)} -> 1006.48 | X9: {=[1]!s_dq_close(X$6,$A9,1)} -> 4518.4 | Y9: {=[1]!s_dq_close(Y$6,$A9,1)} -> 58.78 | Z9: {=[1]!s_dq_close(Z$6,$A9,1)} -> 63.02 | AA9: {=[1]!s_dq_oi(AA$6,$A9)} -> 2260449 | AB9: {=[1]!s_dq_close(AB$6,$A9,1)} -> 2786 | AC9: {=[1]!s_dq_close(AC$6,$A9,1)} -> 3224.86 | AD9: {=[1]!s_dq_close(AD$6,$A9,1)} -> 3144 | AE9: {=[1]!s_dq_close(AE$6,$A9,1)} -> 3294 | AF9: {=[1]!s_dq_close(AF$6,$A9,1)} -> 814.5 | AG9: =[1]!s_dq_close($AG$6,$A9) -> -1193 | AH9: =[1]!s_dq_close($AH$6,A9) -> 6.976
A10: 46026 | B10: 1.8427 | C10: 1.9862 | D10: 1.7839 | E10: 4.19 | F10: 1.5525 | G10: 1.6887 | H10: 3.47 | I10: 1.3522 | J10: 1.94 | K10: 164.3 | M10: {=[1]!s_val_pe_ttm(M$6,$A10)} -> 16.590401 | N10: {=[1]!s_val_pe_ttm(N$6,$A10)} -> 29.240999 | O10: {=[1]!s_val_pb_lf(O$6,$A10)} -> 1.5041 | P10: {=[1]!s_val_pb_lf(P$6,$A10)} -> 5.5286002 | Q10: =[1]!cb_anal_convpremiumratio($Q$6,A10-2) -> 0 | S10: =[1]!cb_anal_straightbondpremiumratio($S$6,A10-3) -> 0 | T10: {=[1]!s_dq_close(T$6,$A10,1)} -> 14.51 | U10: {=[1]!s_dq_close(U$6,$A10,1)} -> 6.989 | V10: {=[1]!s_dq_close(V$6,$A10,1)} -> 98.4594 | W10: {=[1]!s_dq_close(W$6,$A10,1)} -> 977.56 | X10: {=[1]!s_dq_close(X$6,$A10,1)} -> 4341.9 | Y10: {=[1]!s_dq_close(Y$6,$A10,1)} -> 57.33 | Z10: {=[1]!s_dq_close(Z$6,$A10,1)} -> 60.8 | AA10: {=[1]!s_dq_oi(AA$6,$A10)} -> 2149817 | AB10: {=[1]!s_dq_close(AB$6,$A10,1)} -> 2749 | AC10: {=[1]!s_dq_close(AC$6,$A10,1)} -> 3169.43 | AD10: {=[1]!s_dq_close(AD$6,$A10,1)} -> 3122 | AE10: {=[1]!s_dq_close(AE$6,$A10,1)} -> 3270 | AF10: {=[1]!s_dq_close(AF$6,$A10,1)} -> 789.5 | AG10: =[1]!s_dq_close($AG$6,$A10) -> -1126 | AH10: =[1]!s_dq_close($AH$6,A10) -> 6.9699
A11: 46019 | B11: 1.8376 | C11: 1.9817 | D11: 1.8085 | E11: 4.14 | F11: 1.5275 | G11: 1.7189 | H11: 3.49 | I11: 1.3378 | J11: 1.91 | K11: 0 | M11: {=[1]!s_val_pe_ttm(M$6,$A11)} -> 16.5373 | N11: {=[1]!s_val_pe_ttm(N$6,$A11)} -> 29.526699 | O11: {=[1]!s_val_pb_lf(O$6,$A11)} -> 1.4996001 | P11: {=[1]!s_val_pb_lf(P$6,$A11)} -> 5.5826998 | Q11: =[1]!cb_anal_convpremiumratio($Q$6,A11-2) -> 45.958841 | S11: =[1]!cb_anal_straightbondpremiumratio($S$6,A11-3) -> 0 | T11: {=[1]!s_dq_close(T$6,$A11,1)} -> 13.6 | U11: {=[1]!s_dq_close(U$6,$A11,1)} -> 7.0085 | V11: {=[1]!s_dq_close(V$6,$A11,1)} -> 98.0341 | W11: {=[1]!s_dq_close(W$6,$A11,1)} -> 1016.3 | X11: {=[1]!s_dq_close(X$6,$A11,1)} -> 4562 | Y11: {=[1]!s_dq_close(Y$6,$A11,1)} -> 56.93 | Z11: {=[1]!s_dq_close(Z$6,$A11,1)} -> 60.33 | AA11: {=[1]!s_dq_oi(AA$6,$A11)} -> 2086665 | AB11: {=[1]!s_dq_close(AB$6,$A11,1)} -> 2790 | AC11: {=[1]!s_dq_close(AC$6,$A11,1)} -> 3174.86 | AD11: {=[1]!s_dq_close(AD$6,$A11,1)} -> 3118 | AE11: {=[1]!s_dq_close(AE$6,$A11,1)} -> 3283 | AF11: {=[1]!s_dq_close(AF$6,$A11,1)} -> 783 | AG11: =[1]!s_dq_close($AG$6,$A11) -> -1101 | AH11: =[1]!s_dq_close($AH$6,A11) -> 7.0042
A12: 46012 | B12: 1.8308 | C12: 1.9662 | D12: 1.8306 | E12: 4.16 | F12: 1.5725 | G12: 1.719 | H12: 3.51 | I12: 1.3752 | J12: 1.92 | K12: 184.5 | M12: {=[1]!s_val_pe_ttm(M$6,$A12)} -> 16.261299 | N12: {=[1]!s_val_pe_ttm(N$6,$A12)} -> 29.073601 | O12: {=[1]!s_val_pb_lf(O$6,$A12)} -> 1.4686 | P12: {=[1]!s_val_pb_lf(P$6,$A12)} -> 5.4928999 | Q12: =[1]!cb_anal_convpremiumratio($Q$6,A12-2) -> 46.807415 | S12: =[1]!cb_anal_straightbondpremiumratio($S$6,A12-3) -> 0 | T12: {=[1]!s_dq_close(T$6,$A12,1)} -> 14.91 | U12: {=[1]!s_dq_close(U$6,$A12,1)} -> 7.041 | V12: {=[1]!s_dq_close(V$6,$A12,1)} -> 98.7125 | W12: {=[1]!s_dq_close(W$6,$A12,1)} -> 979.9 | X12: {=[1]!s_dq_close(X$6,$A12,1)} -> 4368.7 | Y12: {=[1]!s_dq_close(Y$6,$A12,1)} -> 56.54 | Z12: {=[1]!s_dq_close(Z$6,$A12,1)} -> 60.12 | AA12: {=[1]!s_dq_oi(AA$6,$A12)} -> 2116090 | AB12: {=[1]!s_dq_close(AB$6,$A12,1)} -> 2735 | AC12: {=[1]!s_dq_close(AC$6,$A12,1)} -> 3137.14 | AD12: {=[1]!s_dq_close(AD$6,$A12,1)} -> 3119 | AE12: {=[1]!s_dq_close(AE$6,$A12,1)} -> 3269 | AF12: {=[1]!s_dq_close(AF$6,$A12,1)} -> 780 | AG12: =[1]!s_dq_close($AG$6,$A12) -> -1232 | AH12: =[1]!s_dq_close($AH$6,A12) -> 7.0336
A13: 46005 | B13: 1.8396 | C13: 1.9887 | D13: 1.8439 | E13: 4.19 | F13: 1.6097 | G13: 1.7259 | H13: 3.54 | I13: 1.3951 | J13: 1.93 | K13: 186.9 | M13: {=[1]!s_val_pe_ttm(M$6,$A13)} -> 16.240101 | N13: {=[1]!s_val_pe_ttm(N$6,$A13)} -> 29.0389 | O13: {=[1]!s_val_pb_lf(O$6,$A13)} -> 1.4693 | P13: {=[1]!s_val_pb_lf(P$6,$A13)} -> 5.4923 | Q13: =[1]!cb_anal_convpremiumratio($Q$6,A13-2) -> 47.712401 | S13: =[1]!cb_anal_straightbondpremiumratio($S$6,A13-3) -> 0 | T13: {=[1]!s_dq_close(T$6,$A13,1)} -> 15.74 | U13: {=[1]!s_dq_close(U$6,$A13,1)} -> 7.0554 | V13: {=[1]!s_dq_close(V$6,$A13,1)} -> 98.4012 | W13: {=[1]!s_dq_close(W$6,$A13,1)} -> 970.66 | X13: {=[1]!s_dq_close(X$6,$A13,1)} -> 4329.8 | Y13: {=[1]!s_dq_close(Y$6,$A13,1)} -> 57.53 | Z13: {=[1]!s_dq_close(Z$6,$A13,1)} -> 61.22 | AA13: {=[1]!s_dq_oi(AA$6,$A13)} -> 1925112 | AB13: {=[1]!s_dq_close(AB$6,$A13,1)} -> 2770 | AC13: {=[1]!s_dq_close(AC$6,$A13,1)} -> 3159.43 | AD13: {=[1]!s_dq_close(AD$6,$A13,1)} -> 3060 | AE13: {=[1]!s_dq_close(AE$6,$A13,1)} -> 3232 | AF13: {=[1]!s_dq_close(AF$6,$A13,1)} -> 760.5 | AG13: =[1]!s_dq_close($AG$6,$A13) -> -1293.01 | AH13: =[1]!s_dq_close($AH$6,A13) -> 7.0535
A14: 45998 | B14: 1.848 | C14: 2.0062 | D14: 1.8652 | E14: 4.14 | F14: 1.6296 | G14: 1.7319 | H14: 3.61 | I14: 1.4036 | J14: 1.88 | K14: 0 | M14: {=[1]!s_val_pe_ttm(M$6,$A14)} -> 16.3269 | N14: {=[1]!s_val_pe_ttm(N$6,$A14)} -> 29.375099 | O14: {=[1]!s_val_pb_lf(O$6,$A14)} -> 1.4744 | P14: {=[1]!s_val_pb_lf(P$6,$A14)} -> 5.5479999 | Q14: =[1]!cb_anal_convpremiumratio($Q$6,A14-2) -> 45.348302 | S14: =[1]!cb_anal_straightbondpremiumratio($S$6,A14-3) -> 0 | T14: {=[1]!s_dq_close(T$6,$A14,1)} -> 15.41 | U14: {=[1]!s_dq_close(U$6,$A14,1)} -> 7.0706 | V14: {=[1]!s_dq_close(V$6,$A14,1)} -> 98.983 | W14: {=[1]!s_dq_close(W$6,$A14,1)} -> 961.04 | X14: {=[1]!s_dq_close(X$6,$A14,1)} -> 4227.7 | Y14: {=[1]!s_dq_close(Y$6,$A14,1)} -> 60.14 | Z14: {=[1]!s_dq_close(Z$6,$A14,1)} -> 63.86 | AA14: {=[1]!s_dq_oi(AA$6,$A14)} -> 1783520 | AB14: {=[1]!s_dq_close(AB$6,$A14,1)} -> 2821 | AC14: {=[1]!s_dq_close(AC$6,$A14,1)} -> 3111.43 | AD14: {=[1]!s_dq_close(AD$6,$A14,1)} -> 3157 | AE14: {=[1]!s_dq_close(AE$6,$A14,1)} -> 3320 | AF14: {=[1]!s_dq_close(AF$6,$A14,1)} -> 785.5 | AG14: =[1]!s_dq_close($AG$6,$A14) -> -1291 | AH14: =[1]!s_dq_close($AH$6,A14) -> 7.0691
A15: 45991 | B15: 1.8412 | C15: 1.974 | D15: 1.8396 | E15: 4.02 | F15: 1.6246 | G15: 1.7206 | H15: 3.61 | I15: 1.4183 | J15: 1.79 | K15: 181.8 | M15: {=[1]!s_val_pe_ttm(M$6,$A15)} -> 16.270399 | N15: {=[1]!s_val_pe_ttm(N$6,$A15)} -> 29.241199 | O15: {=[1]!s_val_pb_lf(O$6,$A15)} -> 1.4705 | P15: {=[1]!s_val_pb_lf(P$6,$A15)} -> 5.5253 | Q15: =[1]!cb_anal_convpremiumratio($Q$6,A15-2) -> 44.279974 | S15: =[1]!cb_anal_straightbondpremiumratio($S$6,A15-3) -> 0 | T15: {=[1]!s_dq_close(T$6,$A15,1)} -> 16.35 | U15: {=[1]!s_dq_close(U$6,$A15,1)} -> 7.0794 | V15: {=[1]!s_dq_close(V$6,$A15,1)} -> 99.4391 | W15: {=[1]!s_dq_close(W$6,$A15,1)} -> 953.92 | X15: {=[1]!s_dq_close(X$6,$A15,1)} -> 4256.4 | Y15: {=[1]!s_dq_close(Y$6,$A15,1)} -> 58.48 | Z15: {=[1]!s_dq_close(Z$6,$A15,1)} -> 62.32 | AA15: {=[1]!s_dq_oi(AA$6,$A15)} -> 1297132 | AB15: {=[1]!s_dq_close(AB$6,$A15,1)} -> 3044 | AC15: {=[1]!s_dq_close(AC$6,$A15,1)} -> 3107.43 | AD15: {=[1]!s_dq_close(AD$6,$A15,1)} -> 3110 | AE15: {=[1]!s_dq_close(AE$6,$A15,1)} -> 3302 | AF15: {=[1]!s_dq_close(AF$6,$A15,1)} -> 794 | AG15: =[1]!s_dq_close($AG$6,$A15) -> -1295 | AH15: =[1]!s_dq_close($AH$6,A15) -> 7.0713
A16: 45984 | B16: 1.8166 | C16: 1.9415 | D16: 1.8003 | E16: 4.06 | F16: 1.6191 | G16: 1.6952 | H16: 3.62 | I16: 1.4303 | J16: 1.82 | K16: 194.3 | M16: {=[1]!s_val_pe_ttm(M$6,$A16)} -> 16.1005 | N16: {=[1]!s_val_pe_ttm(N$6,$A16)} -> 28.093 | O16: {=[1]!s_val_pb_lf(O$6,$A16)} -> 1.4552 | P16: {=[1]!s_val_pb_lf(P$6,$A16)} -> 5.3137002 | Q16: =[1]!cb_anal_convpremiumratio($Q$6,A16-2) -> 48.523609 | S16: =[1]!cb_anal_straightbondpremiumratio($S$6,A16-3) -> 0 | T16: {=[1]!s_dq_close(T$6,$A16,1)} -> 23.43 | U16: {=[1]!s_dq_close(U$6,$A16,1)} -> 7.1103 | V16: {=[1]!s_dq_close(V$6,$A16,1)} -> 100.1527 | W16: {=[1]!s_dq_close(W$6,$A16,1)} -> 926.94 | X16: {=[1]!s_dq_close(X$6,$A16,1)} -> 4062.8 | Y16: {=[1]!s_dq_close(Y$6,$A16,1)} -> 57.98 | Z16: {=[1]!s_dq_close(Z$6,$A16,1)} -> 62.51 | AA16: {=[1]!s_dq_oi(AA$6,$A16)} -> 1511379 | AB16: {=[1]!s_dq_close(AB$6,$A16,1)} -> 3012 | AC16: {=[1]!s_dq_close(AC$6,$A16,1)} -> 3075.43 | AD16: {=[1]!s_dq_close(AD$6,$A16,1)} -> 3057 | AE16: {=[1]!s_dq_close(AE$6,$A16,1)} -> 3270 | AF16: {=[1]!s_dq_close(AF$6,$A16,1)} -> 785.5 | AG16: =[1]!s_dq_close($AG$6,$A16) -> -1346.01 | AH16: =[1]!s_dq_close($AH$6,A16) -> 7.1054
A17: 45977 | B17: 1.814 | C17: 1.9371 | D17: 1.8009 | E17: 4.14 | F17: 1.6121 | G17: 1.6992 | H17: 3.7 | I17: 1.4312 | J17: 1.86 | K17: 192.6 | M17: {=[1]!s_val_pe_ttm(M$6,$A17)} -> 16.6427 | N17: {=[1]!s_val_pe_ttm(N$6,$A17)} -> 28.646601 | O17: {=[1]!s_val_pb_lf(O$6,$A17)} -> 1.5045 | P17: {=[1]!s_val_pb_lf(P$6,$A17)} -> 5.3990998 | Q17: =[1]!cb_anal_convpremiumratio($Q$6,A17-2) -> 41.483047 | S17: =[1]!cb_anal_straightbondpremiumratio($S$6,A17-3) -> 0 | T17: {=[1]!s_dq_close(T$6,$A17,1)} -> 19.83 | U17: {=[1]!s_dq_close(U$6,$A17,1)} -> 7.1007 | V17: {=[1]!s_dq_close(V$6,$A17,1)} -> 99.2845 | W17: {=[1]!s_dq_close(W$6,$A17,1)} -> 953.2 | X17: {=[1]!s_dq_close(X$6,$A17,1)} -> 4084.4 | Y17: {=[1]!s_dq_close(Y$6,$A17,1)} -> 59.95 | Z17: {=[1]!s_dq_close(Z$6,$A17,1)} -> 64.29 | AA17: {=[1]!s_dq_oi(AA$6,$A17)} -> 1700146 | AB17: {=[1]!s_dq_close(AB$6,$A17,1)} -> 3092 | AC17: {=[1]!s_dq_close(AC$6,$A17,1)} -> 3124 | AD17: {=[1]!s_dq_close(AD$6,$A17,1)} -> 3053 | AE17: {=[1]!s_dq_close(AE$6,$A17,1)} -> 3256 | AF17: {=[1]!s_dq_close(AF$6,$A17,1)} -> 772.5 | AG17: =[1]!s_dq_close($AG$6,$A17) -> -1313 | AH17: =[1]!s_dq_close($AH$6,A17) -> 7.1001
A18: 45970 | B18: 1.8142 | C18: 1.9489 | D18: 1.7915 | E18: 4.11 | F18: 1.6121 | G18: 1.7006 | H18: 3.63 | I18: 1.4337 | J18: 1.83 | K18: 0 | M18: {=[1]!s_val_pe_ttm(M$6,$A18)} -> 16.647499 | N18: {=[1]!s_val_pe_ttm(N$6,$A18)} -> 28.686701 | O18: {=[1]!s_val_pb_lf(O$6,$A18)} -> 1.5038 | P18: {=[1]!s_val_pb_lf(P$6,$A18)} -> 5.4008002 | Q18: =[1]!cb_anal_convpremiumratio($Q$6,A18-2) -> 41.708389 | S18: =[1]!cb_anal_straightbondpremiumratio($S$6,A18-3) -> 0 | T18: {=[1]!s_dq_close(T$6,$A18,1)} -> 19.08 | U18: {=[1]!s_dq_close(U$6,$A18,1)} -> 7.1225 | V18: {=[1]!s_dq_close(V$6,$A18,1)} -> 99.5477 | W18: {=[1]!s_dq_close(W$6,$A18,1)} -> 921.26 | X18: {=[1]!s_dq_close(X$6,$A18,1)} -> 4007.8 | Y18: {=[1]!s_dq_close(Y$6,$A18,1)} -> 59.84 | Z18: {=[1]!s_dq_close(Z$6,$A18,1)} -> 63.7 | AA18: {=[1]!s_dq_oi(AA$6,$A18)} -> 1577123 | AB18: {=[1]!s_dq_close(AB$6,$A18,1)} -> 3058 | AC18: {=[1]!s_dq_close(AC$6,$A18,1)} -> 3097.71 | AD18: {=[1]!s_dq_close(AD$6,$A18,1)} -> 3034 | AE18: {=[1]!s_dq_close(AE$6,$A18,1)} -> 3245 | AF18: {=[1]!s_dq_close(AF$6,$A18,1)} -> 760.5 | AG18: =[1]!s_dq_close($AG$6,$A18) -> -1315 | AH18: =[1]!s_dq_close($AH$6,A18) -> 7.1252
... A159: 44983 | B159: 2.9126 | C159: 3.0806 | D159: 3.0218 | E159: 3.95 | F159: 2.4678 | G159: 2.8273 | H159: 5.05 | I159: 2.492 | J159: 1.57 | K159: 209.28 | M159: {=[1]!s_val_pe_ttm(M$6,$A159)} -> 13.1553 | N159: {=[1]!s_val_pe_ttm(N$6,$A159)} -> 22.259501 | O159: {=[1]!s_val_pb_lf(O$6,$A159)} -> 1.3459001 | P159: {=[1]!s_val_pb_lf(P$6,$A159)} -> 3.7983 | Q159: =[1]!cb_anal_convpremiumratio($Q$6,A159-2) -> 40.062337 | S159: =[1]!cb_anal_straightbondpremiumratio($S$6,A159-3) -> 0 | T159: {=[1]!s_dq_close(T$6,$A159,1)} -> 21.67 | U159: {=[1]!s_dq_close(U$6,$A159,1)} -> 6.9442 | V159: {=[1]!s_dq_close(V$6,$A159,1)} -> 105.2618 | W159: {=[1]!s_dq_close(W$6,$A159,1)} -> 413.14 | X159: {=[1]!s_dq_close(X$6,$A159,1)} -> 1818 | Y159: {=[1]!s_dq_close(Y$6,$A159,1)} -> 76.45 | Z159: {=[1]!s_dq_close(Z$6,$A159,1)} -> 82.85 | AA159: {=[1]!s_dq_oi(AA$6,$A159)} -> 1301166 | AB159: {=[1]!s_dq_close(AB$6,$A159,1)} -> 3859 | AC159: {=[1]!s_dq_close(AC$6,$A159,1)} -> 4477.14 | AD159: {=[1]!s_dq_close(AD$6,$A159,1)} -> 4224 | AE159: {=[1]!s_dq_close(AE$6,$A159,1)} -> 4296 | AF159: {=[1]!s_dq_close(AF$6,$A159,1)} -> 909.5 | AG159: =[1]!s_dq_close($AG$6,$A159) -> -1826 | AH159: =[1]!s_dq_close($AH$6,A159) -> 6.98
A160: 44976 | B160: 2.892 | C160: 3.0551 | D160: 2.8931 | E160: 3.82 | F160: 2.3821 | G160: 2.6953 | H160: 5 | I160: 2.4472 | J160: 1.46 | K160: 0
A161: 44969 | B161: 2.9003 | C161: 3.0581 | D161: 2.9338 | E161: 3.74 | F161: 2.3271 | G161: 2.728 | H161: 4.89 | I161: 2.438 | J161: 1.41 | K161: 206.21
A162: 44962 | B162: 2.8943 | C162: 3.0544 | D162: 2.9703 | E162: 3.53 | F162: 2.3059 | G162: 2.7057 | H162: 4.79 | I162: 2.4196 | J162: 1.31 | K162: 198.72
A163: 44899 | B163: 2.8676 | C163: 2.9903 | D163: 2.9705 | E163: 3.51 | F163: 2.2812 | G163: 2.6764 | H163: 4.69 | I163: 2.3327 | J163: 1.08 | K163: 202.85

Sheet 股票指标
B1: 上证指数 | E1: 中证转债 | H1: 标普500
A2: 日期 | B2: PE | C2: PB | D2: 股债性价比 | E2: 转股溢价率 | F2: 纯债溢价率 | G2: 隐含波动率 | H2: PE | I2: PB | J2: 股债性价比
A3: =所有指标!A7 -> 46047 | B3: =所有指标!M7 -> 17.0912 | C3: =所有指标!O7 -> 1.5524 | D3: =1/B3-所有指标!B7/100 -> 0.040211643 | E3: 0.30935085 | F3: 0.1776822 | G3: 0.35448332 | H3: =所有指标!N7 -> 29.515699 | I3: =所有指标!P7 -> 5.5702 | J3: =1/H3-所有指标!E7/100 -> -0.0085197254
A4: =所有指标!A8 -> 46040 | B4: =所有指标!M8 -> 17.0165 | C4: =所有指标!O8 -> 1.5445 | D4: =1/B4-所有指标!B8/100 -> 0.04034249 | E4: 0.30576698 | F4: 0.18724607 | G4: 0.35989058 | H4: =所有指标!N8 -> 29.608299 | I4: =所有指标!P8 -> 5.5998998 | J4: =1/H4-所有指标!E8/100 -> -0.0086256859
A5: =所有指标!A9 -> 46033 | B5: =所有指标!M9 -> 17.1359 | C5: =所有指标!O9 -> 1.5535001 | D5: =1/B5-所有指标!B9/100 -> 0.039575015 | E5: 0.32001927 | F5: 0.16724231 | G5: 0.34514641 | H5: =所有指标!N9 -> 29.7474 | I5: =所有指标!P9 -> 5.6240001 | J5: =1/H5-所有指标!E9/100 -> -0.008183617
A6: =所有指标!A10 -> 46026 | B6: =所有指标!M10 -> 16.590401 | C6: =所有指标!O10 -> 1.5041 | D6: =1/B6-所有指标!B10/100 -> 0.04184882 | E6: 0.33193252 | F6: 0.16060899 | G6: 0.35514697 | H6: =所有指标!N10 -> 29.240999 | I6: =所有指标!P10 -> 5.5286002 | J6: =1/H6-所有指标!E10/100 -> -0.0077014423
A7: =所有指标!A11 -> 46019 | B7: =所有指标!M11 -> 16.5373 | C7: =所有指标!O11 -> 1.4996001 | D7: =1/B7-所有指标!B11/100 -> 0.042093363 | E7: 0.36542723 | F7: 0.14048908 | G7: 0.34492041 | H7: =所有指标!N11 -> 29.526699 | I7: =所有指标!P11 -> 5.5826998 | J7: =1/H7-所有指标!E11/100 -> -0.0075323469
A8: =所有指标!A12 -> 46012 | B8: =所有指标!M12 -> 16.261299 | C8: =所有指标!O12 -> 1.4686 | D8: =1/B8-所有指标!B12/100 -> 0.043187702 | E8: 0.36182229 | F8: 0.14837712 | G8: 0.35625005 | H8: =所有指标!N12 -> 29.073601 | I8: =所有指标!P12 -> 5.4928999 | J8: =1/H8-所有指标!E12/100 -> -0.0072045356
A9: =所有指标!A13 -> 46005 | B9: =所有指标!M13 -> 16.240101 | C9: =所有指标!O13 -> 1.4693 | D9: =1/B9-所有指标!B13/100 -> 0.043179972 | E9: 0.35559273 | F9: 0.13546802 | G9: 0.33269427 | H9: =所有指标!N13 -> 29.0389 | I9: =所有指标!P13 -> 5.4923 | J9: =1/H9-所有指标!E13/100 -> -0.0074634343
A10: =所有指标!A14 -> 45998 | B10: =所有指标!M14 -> 16.3269 | C10: =所有指标!O14 -> 1.4744 | D10: =1/B10-所有指标!B14/100 -> 0.042768612 | E10: 0.39544173 | F10: 0.11691179 | G10: 0.33297937 | H10: =所有指标!N14 -> 29.375099 | I10: =所有指标!P14 -> 5.5479999 | J10: =1/H10-所有指标!E14/100 -> -0.0073575617
A11: =所有指标!A15 -> 45991 | B11: =所有指标!M15 -> 16.270399 | C11: =所有指标!O15 -> 1.4705 | D11: =1/B11-所有指标!B15/100 -> 0.043049307 | E11: 0.37087287 | F11: 0.10866348 | G11: 0.30529322 | H11: =所有指标!N15 -> 29.241199 | I11: =所有指标!P15 -> 5.5253 | J11: =1/H11-所有指标!E15/100 -> -0.0060016765
A12: =所有指标!A16 -> 45984 | B12: =所有指标!M16 -> 16.1005 | C12: =所有指标!O16 -> 1.4552 | D12: =1/B12-所有指标!B16/100 -> 0.043943872 | E12: 0.29401857 | F12: 0.14018655 | G12: 0.30431333 | H12: =所有指标!N16 -> 28.093 | I12: =所有指标!P16 -> 5.3137002 | J12: =1/H12-所有指标!E16/100 -> -0.0050039446
A13: =所有指标!A17 -> 45977 | B13: =所有指标!M17 -> 16.6427 | C13: =所有指标!O17 -> 1.5045 | D13: =1/B13-所有指标!B17/100 -> 0.041946404 | E13: 0.2706511 | F13: 0.14047582 | G13: 0.28298021 | H13: =所有指标!N17 -> 28.646601 | I13: =所有指标!P17 -> 5.3990998 | J13: =1/H13-所有指标!E17/100 -> -0.0064918442
A14: =所有指标!A18 -> 45970 | B14: =所有指标!M18 -> 16.647499 | C14: =所有指标!O18 -> 1.5038 | D14: =1/B14-所有指标!B18/100 -> 0.041927083 | E14: 0.25347214 | F14: 0.16000503 | G14: 0.29027639 | H14: =所有指标!N18 -> 28.686701 | I14: =所有指标!P18 -> 5.4008002 | J14: =1/H14-所有指标!E18/100 -> -0.0062406411
... A155: =所有指标!A159 -> 44983 | B155: =所有指标!M159 -> 13.1553 | C155: =所有指标!O159 -> 1.3459001 | D155: =1/B155-所有指标!B159/100 -> 0.046888989 | E155: 0.30495483 | F155: 0.29363272 | G155: 0.40814012 | H155: =所有指标!N159 -> 22.259501 | I155: =所有指标!P159 -> 3.7983 | J155: =1/H155-所有指标!E159/100 -> 0.0054246379

Sheet 债券指标
B1: 10年国开 | E1: 2年AAA信用 | H1: 10年美债
A2: 日期 | B2: 收益率 | C2: 信用利差 | D2: 期限利差 | E2: 收益率 | F2: 信用利差 | G2: 期限利差 | H2: 收益率 | I2: 期限利率 | J2: VIX
A3: =所有指标!A7 -> 46047 | B3: =所有指标!C7 -> 1.9735 | C3: =(所有指标!C7-所有指标!B7)*100 -> 14.37 | D3: =(所有指标!C7-所有指标!F7)*100 -> 39.76 | E3: =所有指标!D7 -> 1.7741 | F3: =(所有指标!D7-所有指标!I7)*100 -> 37.82 | G3: =(所有指标!D7-所有指标!G7)*100 -> 10.2 | H3: =所有指标!E7 -> 4.24 | I3: =(所有指标!E7-所有指标!H7)*100 -> 71 | J3: =所有指标!T7 -> 16.09
A4: =所有指标!A8 -> 46040 | B4: =所有指标!C8 -> 2.0152 | C4: =(所有指标!C8-所有指标!B8)*100 -> 17.28 | D4: =(所有指标!C8-所有指标!F8)*100 -> 42.1 | E4: =所有指标!D8 -> 1.7915 | F4: =(所有指标!D8-所有指标!I8)*100 -> 38.72 | G4: =(所有指标!D8-所有指标!G8)*100 -> 9.29 | H4: =所有指标!E8 -> 4.24 | I4: =(所有指标!E8-所有指标!H8)*100 -> 69 | J4: =所有指标!T8 -> 15.86
A5: =所有指标!A9 -> 46033 | B5: =所有指标!C9 -> 2.0287 | C5: =(所有指标!C9-所有指标!B9)*100 -> 15.05 | D5: =(所有指标!C9-所有指标!F9)*100 -> 45.08 | E5: =所有指标!D9 -> 1.8057 | F5: =(所有指标!D9-所有指标!I9)*100 -> 36.95 | G5: =(所有指标!D9-所有指标!G9)*100 -> 11.19 | H5: =所有指标!E9 -> 4.18 | I5: =(所有指标!E9-所有指标!H9)*100 -> 66 | J5: =所有指标!T9 -> 14.49
A6: =所有指标!A10 -> 46026 | B6: =所有指标!C10 -> 1.9862 | C6: =(所有指标!C10-所有指标!B10)*100 -> 14.35 | D6: =(所有指标!C10-所有指标!F10)*100 -> 43.37 | E6: =所有指标!D10 -> 1.7839 | F6: =(所有指标!D10-所有指标!I10)*100 -> 43.17 | G6: =(所有指标!D10-所有指标!G10)*100 -> 9.52 | H6: =所有指标!E10 -> 4.19 | I6: =(所有指标!E10-所有指标!H10)*100 -> 72 | J6: =所有指标!T10 -> 14.51
A7: =所有指标!A11 -> 46019 | B7: =所有指标!C11 -> 1.9817 | C7: =(所有指标!C11-所有指标!B11)*100 -> 14.41 | D7: =(所有指标!C11-所有指标!F11)*100 -> 45.42 | E7: =所有指标!D11 -> 1.8085 | F7: =(所有指标!D11-所有指标!I11)*100 -> 47.07 | G7: =(所有指标!D11-所有指标!G11)*100 -> 8.96 | H7: =所有指标!E11 -> 4.14 | I7: =(所有指标!E11-所有指标!H11)*100 -> 65 | J7: =所有指标!T11 -> 13.6
A8: =所有指标!A12 -> 46012 | B8: =所有指标!C12 -> 1.9662 | C8: =(所有指标!C12-所有指标!B12)*100 -> 13.54 | D8: =(所有指标!C12-所有指标!F12)*100 -> 39.37 | E8: =所有指标!D12 -> 1.8306 | F8: =(所有指标!D12-所有指标!I12)*100 -> 45.54 | G8: =(所有指标!D12-所有指标!G12)*100 -> 11.16 | H8: =所有指标!E12 -> 4.16 | I8: =(所有指标!E12-所有指标!H12)*100 -> 65 | J8: =所有指标!T12 -> 14.91
A9: =所有指标!A13 -> 46005 | B9: =所有指标!C13 -> 1.9887 | C9: =(所有指标!C13-所有指标!B13)*100 -> 14.91 | D9: =(所有指标!C13-所有指标!F13)*100 -> 37.9 | E9: =所有指标!D13 -> 1.8439 | F9: =(所有指标!D13-所有指标!I13)*100 -> 44.88 | G9: =(所有指标!D13-所有指标!G13)*100 -> 11.8 | H9: =所有指标!E13 -> 4.19 | I9: =(所有指标!E13-所有指标!H13)*100 -> 65 | J9: =所有指标!T13 -> 15.74
A10: =所有指标!A14 -> 45998 | B10: =所有指标!C14 -> 2.0062 | C10: =(所有指标!C14-所有指标!B14)*100 -> 15.82 | D10: =(所有指标!C14-所有指标!F14)*100 -> 37.66 | E10: =所有指标!D14 -> 1.8652 | F10: =(所有指标!D14-所有指标!I14)*100 -> 46.16 | G10: =(所有指标!D14-所有指标!G14)*100 -> 13.33 | H10: =所有指标!E14 -> 4.14 | I10: =(所有指标!E14-所有指标!H14)*100 -> 53 | J10: =所有指标!T14 -> 15.41
A11: =所有指标!A15 -> 45991 | B11: =所有指标!C15 -> 1.974 | C11: =(所有指标!C15-所有指标!B15)*100 -> 13.28 | D11: =(所有指标!C15-所有指标!F15)*100 -> 34.94 | E11: =所有指标!D15 -> 1.8396 | F11: =(所有指标!D15-所有指标!I15)*100 -> 42.13 | G11: =(所有指标!D15-所有指标!G15)*100 -> 11.9 | H11: =所有指标!E15 -> 4.02 | I11: =(所有指标!E15-所有指标!H15)*100 -> 41 | J11: =所有指标!T15 -> 16.35
A12: =所有指标!A16 -> 45984 | B12: =所有指标!C16 -> 1.9415 | C12: =(所有指标!C16-所有指标!B16)*100 -> 12.49 | D12: =(所有指标!C16-所有指标!F16)*100 -> 32.24 | E12: =所有指标!D16 -> 1.8003 | F12: =(所有指标!D16-所有指标!I16)*100 -> 37 | G12: =(所有指标!D16-所有指标!G16)*100 -> 10.51 | H12: =所有指标!E16 -> 4.06 | I12: =(所有指标!E16-所有指标!H16)*100 -> 44 | J12: =所有指标!T16 -> 23.43
A13: =所有指标!A17 -> 45977 | B13: =所有指标!C17 -> 1.9371 | C13: =(所有指标!C17-所有指标!B17)*100 -> 12.31 | D13: =(所有指标!C17-所有指标!F17)*100 -> 32.5 | E13: =所有指标!D17 -> 1.8009 | F13: =(所有指标!D17-所有指标!I17)*100 -> 36.97 | G13: =(所有指标!D17-所有指标!G17)*100 -> 10.17 | H13: =所有指标!E17 -> 4.14 | I13: =(所有指标!E17-所有指标!H17)*100 -> 44 | J13: =所有指标!T17 -> 19.83
A14: =所有指标!A18 -> 45970 | B14: =所有指标!C18 -> 1.9489 | C14: =(所有指标!C18-所有指标!B18)*100 -> 13.47 | D14: =(所有指标!C18-所有指标!F18)*100 -> 33.68 | E14: =所有指标!D18 -> 1.7915 | F14: =(所有指标!D18-所有指标!I18)*100 -> 35.78 | G14: =(所有指标!D18-所有指标!G18)*100 -> 9.09 | H14: =所有指标!E18 -> 4.11 | I14: =(所有指标!E18-所有指标!H18)*100 -> 48 | J14: =所有指标!T18 -> 19.08
... A155: =所有指标!A159 -> 44983 | B155: =所有指标!C159 -> 3.0806 | C155: =(所有指标!C159-所有指标!B159)*100 -> 16.8 | D155: =(所有指标!C159-所有指标!F159)*100 -> 61.28 | E155: =所有指标!D159 -> 3.0218 | F155: =(所有指标!D159-所有指标!I159)*100 -> 52.98 | G155: =(所有指标!D159-所有指标!G159)*100 -> 19.45 | H155: =所有指标!E159 -> 3.95 | I155: =(所有指标!E159-所有指标!H159)*100 -> -110 | J155: =所有指标!T159 -> 21.67

Sheet 汇率指标
B1: USDCNY | E1: 锁汇成本
A2: 日期 | B2: 中间价 | C2: 中美利差 | D2: 美元指数 | E2: 锁汇成本 | F2: 掉期点1Y | G2: 美元兑离岸人民币CNH
A3: =所有指标!A7 -> 46047 | B3: =所有指标!U7 -> 6.9642 | C3: =(所有指标!B7-所有指标!E7)*100 -> -241.02 | D3: =所有指标!V7 -> 97.5053 | E3: =-所有指标!AG7/10000/所有指标!AH7 -> 0.0177875 | F3: =所有指标!AG7 -> -1236 | G3: =所有指标!AH7 -> 6.9487
A4: =所有指标!A8 -> 46040 | B4: =所有指标!U8 -> 6.969 | C4: =(所有指标!B8-所有指标!E8)*100 -> -239.76 | D4: =所有指标!V8 -> 99.3691 | E4: =-所有指标!AG8/10000/所有指标!AH8 -> 0.017323535 | F4: =所有指标!AG8 -> -1207 | G4: =所有指标!AH8 -> 6.9674
A5: =所有指标!A9 -> 46033 | B5: =所有指标!U9 -> 6.9821 | C5: =(所有指标!B9-所有指标!E9)*100 -> -230.18 | D5: =所有指标!V9 -> 99.1368 | E5: =-所有指标!AG9/10000/所有指标!AH9 -> 0.017101491 | F5: =所有指标!AG9 -> -1193 | G5: =所有指标!AH9 -> 6.976
A6: =所有指标!A10 -> 46026 | B6: =所有指标!U10 -> 6.989 | C6: =(所有指标!B10-所有指标!E10)*100 -> -234.73 | D6: =所有指标!V10 -> 98.4594 | E6: =-所有指标!AG10/10000/所有指标!AH10 -> 0.016155182 | F6: =所有指标!AG10 -> -1126 | G6: =所有指标!AH10 -> 6.9699
A7: =所有指标!A11 -> 46019 | B7: =所有指标!U11 -> 7.0085 | C7: =(所有指标!B11-所有指标!E11)*100 -> -230.24 | D7: =所有指标!V11 -> 98.0341 | E7: =-所有指标!AG11/10000/所有指标!AH11 -> 0.01571914 | F7: =所有指标!AG11 -> -1101 | G7: =所有指标!AH11 -> 7.0042
A8: =所有指标!A12 -> 46012 | B8: =所有指标!U12 -> 7.041 | C8: =(所有指标!B12-所有指标!E12)*100 -> -232.92 | D8: =所有指标!V12 -> 98.7125 | E8: =-所有指标!AG12/10000/所有指标!AH12 -> 0.017515924 | F8: =所有指标!AG12 -> -1232 | G8: =所有指标!AH12 -> 7.0336
A9: =所有指标!A13 -> 46005 | B9: =所有指标!U13 -> 7.0554 | C9: =(所有指标!B13-所有指标!E13)*100 -> -235.04 | D9: =所有指标!V13 -> 98.4012 | E9: =-所有指标!AG13/10000/所有指标!AH13 -> 0.018331467 | F9: =所有指标!AG13 -> -1293.01 | G9: =所有指标!AH13 -> 7.0535
A10: =所有指标!A14 -> 45998 | B10: =所有指标!U14 -> 7.0706 | C10: =(所有指标!B14-所有指标!E14)*100 -> -229.2 | D10: =所有指标!V14 -> 98.983 | E10: =-所有指标!AG14/10000/所有指标!AH14 -> 0.018262579 | F10: =所有指标!AG14 -> -1291 | G10: =所有指标!AH14 -> 7.0691
A11: =所有指标!A15 -> 45991 | B11: =所有指标!U15 -> 7.0794 | C11: =(所有指标!B15-所有指标!E15)*100 -> -217.88 | D11: =所有指标!V15 -> 99.4391 | E11: =-所有指标!AG15/10000/所有指标!AH15 -> 0.018313464 | F11: =所有指标!AG15 -> -1295 | G11: =所有指标!AH15 -> 7.0713
A12: =所有指标!A16 -> 45984 | B12: =所有指标!U16 -> 7.1103 | C12: =(所有指标!B16-所有指标!E16)*100 -> -224.34 | D12: =所有指标!V16 -> 100.1527 | E12: =-所有指标!AG16/10000/所有指标!AH16 -> 0.01894348 | F12: =所有指标!AG16 -> -1346.01 | G12: =所有指标!AH16 -> 7.1054
A13: =所有指标!A17 -> 45977 | B13: =所有指标!U17 -> 7.1007 | C13: =(所有指标!B17-所有指标!E17)*100 -> -232.6 | D13: =所有指标!V17 -> 99.2845 | E13: =-所有指标!AG17/10000/所有指标!AH17 -> 0.018492697 | F13: =所有指标!AG17 -> -1313 | G13: =所有指标!AH17 -> 7.1001
A14: =所有指标!A18 -> 45970 | B14: =所有指标!U18 -> 7.1225 | C14: =(所有指标!B18-所有指标!E18)*100 -> -229.58 | D14: =所有指标!V18 -> 99.5477 | E14: =-所有指标!AG18/10000/所有指标!AH18 -> 0.018455622 | F14: =所有指标!AG18 -> -1315 | G14: =所有指标!AH18 -> 7.1252
... A155: =所有指标!A159 -> 44983 | B155: =所有指标!U159 -> 6.9442 | C155: =(所有指标!B159-所有指标!E159)*100 -> -103.74 | D155: =所有指标!V159 -> 105.2618 | E155: =-所有指标!AG159/10000/所有指标!AH159 -> 0.026160458 | F155: =所有指标!AG159 -> -1826 | G155: =所有指标!AH159 -> 6.98

Sheet 商品指标
B1: 沪金 | E1: 螺纹钢 | H1: 原油 | K1: 豆粕
A2: 日期 | B2: 内外盘价差 | C2: 美国实际利率 | D2: USDCNY中间价 | E2: 螺卷差 | F2: 铁矿 | G2: USDCNY中间价 | H2: WTI与布油价差 | I2: 美元指数 | J2: USDCNY中间价 | K2: 期现价差 | L2: 持仓 | M2: USDCNY中间价
A3: =所有指标!A7 -> 46047 | B3: =所有指标!W7-所有指标!X7*所有指标!U7/31.1035 -> -0.096332567 | C3: =所有指标!J7 -> 1.92 | D3: =所有指标!U7 -> 6.9642 | E3: =所有指标!AE7-所有指标!AD7 -> 163 | F3: =所有指标!AF7 -> 795 | G3: =所有指标!U7 -> 6.9642 | H3: =所有指标!Y7-所有指标!Z7 -> -4.16 | I3: =所有指标!V7 -> 97.5053 | J3: =所有指标!U7 -> 6.9642 | K3: =所有指标!AB7-所有指标!AC7 -> -443.29 | L3: =所有指标!AA7 -> 2161911 | M3: =所有指标!U7 -> 6.9642
A4: =所有指标!A8 -> 46040 | B4: =所有指标!W8-所有指标!X8*所有指标!U8/31.1035 -> 1.4049615 | C4: =所有指标!J8 -> 1.91 | D4: =所有指标!U8 -> 6.969 | E4: =所有指标!AE8-所有指标!AD8 -> 152 | F4: =所有指标!AF8 -> 812 | G4: =所有指标!U8 -> 6.969 | H4: =所有指标!Y8-所有指标!Z8 -> -4.98 | I4: =所有指标!V8 -> 99.3691 | J4: =所有指标!U8 -> 6.969 | K4: =所有指标!AB8-所有指标!AC8 -> -469.29 | L4: =所有指标!AA8 -> 2238668 | M4: =所有指标!U8 -> 6.969
A5: =所有指标!A9 -> 46033 | B5: =所有指标!W9-所有指标!X9*所有指标!U9/31.1035 -> -7.8084447 | C5: =所有指标!J9 -> 1.9 | D5: =所有指标!U9 -> 6.9821 | E5: =所有指标!AE9-所有指标!AD9 -> 150 | F5: =所有指标!AF9 -> 814.5 | G5: =所有指标!U9 -> 6.9821 | H5: =所有指标!Y9-所有指标!Z9 -> -4.24 | I5: =所有指标!V9 -> 99.1368 | J5: =所有指标!U9 -> 6.9821 | K5: =所有指标!AB9-所有指标!AC9 -> -438.86 | L5: =所有指标!AA9 -> 2260449 | M5: =所有指标!U9 -> 6.9821
A6: =所有指标!A10 -> 46026 | B6: =所有指标!W10-所有指标!X10*所有指标!U10/31.1035 -> 1.9289906 | C6: =所有指标!J10 -> 1.94 | D6: =所有指标!U10 -> 6.989 | E6: =所有指标!AE10-所有指标!AD10 -> 148 | F6: =所有指标!AF10 -> 789.5 | G6: =所有指标!U10 -> 6.989 | H6: =所有指标!Y10-所有指标!Z10 -> -3.47 | I6: =所有指标!V10 -> 98.4594 | J6: =所有指标!U10 -> 6.989 | K6: =所有指标!AB10-所有指标!AC10 -> -420.43 | L6: =所有指标!AA10 -> 2149817 | M6: =所有指标!U10 -> 6.989
A7: =所有指标!A11 -> 46019 | B7: =所有指标!W11-所有指标!X11*所有指标!U11/31.1035 -> -11.647884 | C7: =所有指标!J11 -> 1.91 | D7: =所有指标!U11 -> 7.0085 | E7: =所有指标!AE11-所有指标!AD11 -> 165 | F7: =所有指标!AF11 -> 783 | G7: =所有指标!U11 -> 7.0085 | H7: =所有指标!Y11-所有指标!Z11 -> -3.4 | I7: =所有指标!V11 -> 98.0341 | J7: =所有指标!U11 -> 7.0085 | K7: =所有指标!AB11-所有指标!AC11 -> -384.86 | L7: =所有指标!AA11 -> 2086665 | M7: =所有指标!U11 -> 7.0085
A8: =所有指标!A12 -> 46012 | B8: =所有指标!W12-所有指标!X12*所有指标!U12/31.1035 -> -9.0567637 | C8: =所有指标!J12 -> 1.92 | D8: =所有指标!U12 -> 7.041 | E8: =所有指标!AE12-所有指标!AD12 -> 150 | F8: =所有指标!AF12 -> 780 | G8: =所有指标!U12 -> 7.041 | H8: =所有指标!Y12-所有指标!Z12 -> -3.58 | I8: =所有指标!V12 -> 98.7125 | J8: =所有指标!U12 -> 7.041 | K8: =所有指标!AB12-所有指标!AC12 -> -402.14 | L8: =所有指标!AA12 -> 2116090 | M8: =所有指标!U12 -> 7.041
A9: =所有指标!A13 -> 46005 | B9: =所有指标!W13-所有指标!X13*所有指标!U13/31.1035 -> -11.495414 | C9: =所有指标!J13 -> 1.93 | D9: =所有指标!U13 -> 7.0554 | E9: =所有指标!AE13-所有指标!AD13 -> 172 | F9: =所有指标!AF13 -> 760.5 | G9: =所有指标!U13 -> 7.0554 | H9: =所有指标!Y13-所有指标!Z13 -> -3.69 | I9: =所有指标!V13 -> 98.4012 | J9: =所有指标!U13 -> 7.0554 | K9: =所有指标!AB13-所有指标!AC13 -> -389.43 | L9: =所有指标!AA13 -> 1925112 | M9: =所有指标!U13 -> 7.0554
A10: =所有指标!A14 -> 45998 | B10: =所有指标!W14-所有指标!X14*所有指标!U14/31.1035 -> -0.02147604 | C10: =所有指标!J14 -> 1.88 | D10: =所有指标!U14 -> 7.0706 | E10: =所有指标!AE14-所有指标!AD14 -> 163 | F10: =所有指标!AF14 -> 785.5 | G10: =所有指标!U14 -> 7.0706 | H10: =所有指标!Y14-所有指标!Z14 -> -3.72 | I10: =所有指标!V14 -> 98.983 | J10: =所有指标!U14 -> 7.0706 | K10: =所有指标!AB14-所有指标!AC14 -> -290.43 | L10: =所有指标!AA14 -> 1783520 | M10: =所有指标!U14 -> 7.0706
A11: =所有指标!A15 -> 45991 | B11: =所有指标!W15-所有指标!X15*所有指标!U15/31.1035 -> -14.869948 | C11: =所有指标!J15 -> 1.79 | D11: =所有指标!U15 -> 7.0794 | E11: =所有指标!AE15-所有指标!AD15 -> 192 | F11: =所有指标!AF15 -> 794 | G11: =所有指标!U15 -> 7.0794 | H11: =所有指标!Y15-所有指标!Z15 -> -3.84 | I11: =所有指标!V15 -> 99.4391 | J11: =所有指标!U15 -> 7.0794 | K11: =所有指标!AB15-所有指标!AC15 -> -63.43 | L11: =所有指标!AA15 -> 1297132 | M11: =所有指标!U15 -> 7.0794
A12: =所有指标!A16 -> 45984 | B12: =所有指标!W16-所有指标!X16*所有指标!U16/31.1035 -> -1.8212918 | C12: =所有指标!J16 -> 1.82 | D12: =所有指标!U16 -> 7.1103 | E12: =所有指标!AE16-所有指标!AD16 -> 213 | F12: =所有指标!AF16 -> 785.5 | G12: =所有指标!U16 -> 7.1103 | H12: =所有指标!Y16-所有指标!Z16 -> -4.53 | I12: =所有指标!V16 -> 100.1527 | J12: =所有指标!U16 -> 7.1103 | K12: =所有指标!AB16-所有指标!AC16 -> -63.43 | L12: =所有指标!AA16 -> 1511379 | M12: =所有指标!U16 -> 7.1103
A13: =所有指标!A17 -> 45977 | B13: =所有指标!W17-所有指标!X17*所有指标!U17/31.1035 -> 20.761558 | C13: =所有指标!J17 -> 1.86 | D13: =所有指标!U17 -> 7.1007 | E13: =所有指标!AE17-所有指标!AD17 -> 203 | F13: =所有指标!AF17 -> 772.5 | G13: =所有指标!U17 -> 7.1007 | H13: =所有指标!Y17-所有指标!Z17 -> -4.34 | I13: =所有指标!V17 -> 99.2845 | J13: =所有指标!U17 -> 7.1007 | K13: =所有指标!AB17-所有指标!AC17 -> -32 | L13: =所有指标!AA17 -> 1700146 | M13: =所有指标!U17 -> 7.1007
A14: =所有指标!A18 -> 45970 | B14: =所有指标!W18-所有指标!X18*所有指标!U18/31.1035 -> 3.499764 | C14: =所有指标!J18 -> 1.83 | D14: =所有指标!U18 -> 7.1225 | E14: =所有指标!AE18-所有指标!AD18 -> 211 | F14: =所有指标!AF18 -> 760.5 | G14: =所有指标!U18 -> 7.1225 | H14: =所有指标!Y18-所有指标!Z18 -> -3.86 | I14: =所有指标!V18 -> 99.5477 | J14: =所有指标!U18 -> 7.1225 | K14: =所有指标!AB18-所有指标!AC18 -> -39.71 | L14: =所有指标!AA18 -> 1577123 | M14: =所有指标!U18 -> 7.1225
... A155: =所有指标!A159 -> 44983 | B155: =所有指标!W159-所有指标!X159*所有指标!U159/31.1035 -> 7.2514151 | C155: =所有指标!J159 -> 1.57 | D155: =所有指标!U159 -> 6.9442 | E155: =所有指标!AE159-所有指标!AD159 -> 72 | F155: =所有指标!AF159 -> 909.5 | G155: =所有指标!U159 -> 6.9442 | H155: =所有指标!Y159-所有指标!Z159 -> -6.4 | I155: =所有指标!V159 -> 105.2618 | J155: =所有指标!U159 -> 6.9442 | K155: =所有指标!AB159-所有指标!AC159 -> -618.14 | L155: =所有指标!AA159 -> 1301166 | M155: =所有指标!U159 -> 6.9442
